PlugSy-0.2.31.dist-info/DESCRIPTION.rst
PlugSy-0.2.31.dist-info/METADATA
PlugSy-0.2.31.dist-info/RECORD
PlugSy-0.2.31.dist-info/WHEEL
PlugSy-0.2.31.dist-info/entry_points.txt
PlugSy-0.2.31.dist-info/metadata.json
PlugSy-0.2.31.dist-info/top_level.txt
plugsy/AbstractPlugin.py
plugsy/Config.py
plugsy/Exceptions.py
plugsy/LaunchPlugsyGui.py
plugsy/Logger.py
plugsy/Plugsy.py
plugsy/__init__.py
plugsy/sdk/Exceptions.py
plugsy/sdk/Plugin.py
plugsy/sdk/Sdk.py
plugsy/sdk/__init__.py
plugsy/sdk/PluginTemplate/Config.py
plugsy/sdk/PluginTemplate/PluginTemplate.py
plugsy/sdk/PluginTemplate/__init__.py
plugsy/sdk/gui/ConfirmationDialogs.py
plugsy/sdk/gui/SdkGui.py
plugsy/sdk/gui/SdkGuiAbs.py
plugsy/sdk/gui/__init__.py
plugsy/utils/LaunchPlugsyGui.py
plugsy/utils/Logger.py
plugsy/utils/__init__.py
plugsy/utils/toposort.py
sample_plugins/__init__.py
