Metadata-Version: 2.0
Name: PlugSy
Version: 0.2.31
Summary: Threaded plugin system and SDK
Home-page: https://github.com/sithis993/PlugSy
Author: Sithis
Author-email: sithis999@gmail.com
License: UNKNOWN
Platform: UNKNOWN
Requires-Dist: wxPython (==4.0.1); "win" in sys_platform
